{
  "NAME": "",
  "SERVER_HOST": "",
  "SERVER_PORT": 1234,
  "JWT_SECRET": "",
  "DB_USER": "",
  "DB_PORT": 1234,
  "DB_HOST": "",
  "DB_PASSWORD": "",
  "DB_NAME": "",
  "DB_SCHEMA": "",
  "AWS_REGION": "",
  "AWS_ACCESSKEY": "",
  "AWS_SECRETKEY": "",
  "AWS_TOKEN": "",
  "AWS_BUCKET_QRCODE": "",
  "AWS_BUCKET_CONTRACTS": "",
  "AWS_BUCKET_GALLERY": "",
  "AWS_SES_EMAIL_FROM": "",
  "REDIS_ADDRESS": "",
  "REDIS_PASSWORD": "",
  "RABBIT_MQ_NAME": "",
  "RABBIT_MQ_QUEUE": "",
  "RABBIT_MQ_ADDRESS-QUEUE": "",
  "MONGO_ADDRESS": "",
  "MONGO_DBNAME": "",
  "MONGO_COLLECTION": "",
  "GOOGLE_CLOUD_SECRET_KEY": "",
  "GOOGLE_MATRIX_DISTANCE_API_URL": "",
  "STRIPE_PUBLIC_KEY": "",
  "STRIPE_SECRET_KEY": "",
  "DROPBOX_API_URL": "",
  "DROPBOX_SECRET_KEY": "",
  "DROPBOX_CC_EMAIL": ""
}
